ufiber_client3/olt.py
ufiber_client3-1.0.1.dist-info/METADATA
ufiber_client3-1.0.1.dist-info/WHEEL
ufiber_client3-1.0.1.dist-info/top_level.txt
ufiber_client3-1.0.1.dist-info/RECORD
