Metadata-Version: 2.1
Name: ufiber-client3
Version: 1.0.1
Summary: Ubiquiti UFiber Client for firmware version 3
Author-email: Arturo Baldo <baldoarturo@mail.com>
Project-URL: Homepage, https://github.com/baldoarturo/ufiber-client
Keywords: ubiquiti,ufiber,gpon,netowrk,automation,networking
Classifier: License :: OSI Approved :: GNU General Public License v3 or later (GPLv3+)
Classifier: Programming Language :: Python
Classifier: Programming Language :: Python :: 3
Requires-Python: >=3.8
Requires-Dist: requests
